{
  "port": "NetworkingLibraries-Main",
  "name": "Hiredis",
  "version": "1.3.0",
  "architectures": ["x86_64"],
  "description": "Minimalistic C client for Redis",
  "website": "https://github.com/redis/hiredis",
  "installedFiles": [],
  "dependencies": [
    {
      "port": "SystemBase-Main",
      "name": "SystemBase",
      "version": ">=0.2.0",
      "options": []
    }
  ],
  "kernelDependencies": [],
  "options": [],
  "uniqueDependencies": [],
  "uniqueOptions": [],
  "selectedDependencies": [],
  "allowCodependencies": []
}
